[{"type":"callout","rich":[{"text":"https://melbournepickup.com/","href":"https://melbournepickup.com/"}],"color":"gray_background","icon":"🔗"},{"type":"callout","rich":[{"text":"목표","bold":true},{"text":"\nUber 스타일 가격 계산 기능을 포함한 웹사이트 개발"}],"color":"gray_background","icon":"🎯"},{"type":"heading_2","rich":[{"text":"미리보기"}]},{"type":"image","src":"assets/img/projects/gmaps-distance/01.gif","caption":[]},{"type":"heading_2","rich":[{"text":"자세한 수행 과정","bold":true}]},{"type":"paragraph","rich":[{"text":"클라이언트는 Uber 및 기타 배달 앱과 유사한 요금 계산기를 통해 픽업 요금 견적을 받아볼 수 있는 웹사이트를 필요로 했습니다. Google Maps API를 사용하여 이를 구현해보았습니다."}]},{"type":"heading_3","rich":[{"text":"1. Google Maps Platform API"}],"color":"green_background"},{"type":"column_list","children":[{"type":"column","children":[{"type":"image","src":"assets/img/projects/gmaps-distance/02.png","caption":[]}]},{"type":"column","children":[{"type":"image","src":"assets/img/projects/gmaps-distance/03.png","caption":[]}]}]},{"type":"paragraph","rich":[{"text":"Google Maps API의 사용은 원활했습니다. API 키를 취득하고 구현하는 것은 간단했으며, 몇 분 내에 즉시 사용할 수 있었습니다."}]},{"type":"heading_3","rich":[{"text":"2. My Maps 기능 활용"}],"color":"green_background"},{"type":"column_list","children":[{"type":"column","children":[{"type":"image","src":"assets/img/projects/gmaps-distance/04.png","caption":[]}]},{"type":"column","children":[{"type":"image","src":"assets/img/projects/gmaps-distance/05.png","caption":[]}]}]},{"type":"paragraph","rich":[{"text":"사용자 경험을 더욱 향상시키기 위해 Maps API와는 별개의 사용자 친화적인 기능인 \"My Maps\"를 통합했습니다."}]},{"type":"heading_3","rich":[{"text":"3. 계산 기능 구현"}],"color":"green_background"},{"type":"column_list","children":[{"type":"column","children":[{"type":"image","src":"assets/img/projects/gmaps-distance/06.png","caption":[{"text":"Google gave us an function that return distance"}]}]},{"type":"column","children":[{"type":"image","src":"assets/img/projects/gmaps-distance/07.png","caption":[]}]}]},{"type":"paragraph","rich":[{"text":"Google은 위치 간의 거리를 반환하는 함수를 제공합니다. 클라이언트의 요구 사항은 사용자가 \"시간\", \"차량 유형\", \"거리\"(공항 및 목적지 포함), \"짐\" 등의 변수를 기반으로 대략적인 가격을 계산할 수 있도록 하는 것이었습니다. 클라이언트와 충분히 논의한 후, 대략적인 가격을 계산하는 공식을 개발했습니다."}]},{"type":"column_list","children":[{"type":"column","children":[{"type":"image","src":"assets/img/projects/gmaps-distance/08.png","caption":[]}]},{"type":"column","children":[{"type":"image","src":"assets/img/projects/gmaps-distance/09.png","caption":[]}]}]},{"type":"heading_3","rich":[{"text":"4. Python 웹 크롤링 (네이버 블로그에서 사진 다운로드하기)","bold":true}],"color":"green_background"},{"type":"column_list","children":[{"type":"column","children":[{"type":"image","src":"assets/img/projects/gmaps-distance/10.png","caption":[]},{"type":"image","src":"assets/img/projects/gmaps-distance/11.png","caption":[]}]},{"type":"column","children":[{"type":"image","src":"assets/img/projects/gmaps-distance/12.png","caption":[]}]}]},{"type":"paragraph","rich":[{"text":"클라이언트분이 컴퓨터를 잘 못쓰시는 분이어서, 원본 이미지를 얻는 것이 불가능했습니다. 그래서 저는 클라이언트의 블로그에서 Python, Chromedriver, Selenium을 사용하여 사진을 크롤링하기로 결정했습니다."}]},{"type":"child_page","title":"View Full Code","slug":"gmaps-distance-sub-4f4e9866"},{"type":"paragraph","rich":[{"text":"Source Code : ","bold":true},{"text":"https://github.com/urustin/masterTour","href":"https://github.com/urustin/masterTour"}]},{"type":"heading_2","rich":[{"text":"Review"}]},{"type":"callout","rich":[{"text":"배운 점","bold":true}],"color":"blue_background","icon":"👍","children":[{"type":"bulleted_list_item","rich":[{"text":"Google Maps API"}]},{"type":"bulleted_list_item","rich":[{"text":"Cpanel 기반 웹 호스팅 사용(특히 Fast Comet)."}]}]},{"type":"callout","rich":[{"text":"추가 과제","bold":true}],"color":"pink_background","icon":"🔥","children":[{"type":"bulleted_list_item","rich":[{"text":"웹 크롤링에 대한 추가적 학습"}]}]}]